pyexoplaneteu/__init__.py
pyexoplaneteu/config.py
pyexoplaneteu/pyexoplaneteu.py
pyexoplaneteu/utils.py
pyExoplaneteu-1.0.3.dist-info/LICENSE
pyExoplaneteu-1.0.3.dist-info/METADATA
pyExoplaneteu-1.0.3.dist-info/WHEEL
pyExoplaneteu-1.0.3.dist-info/top_level.txt
pyExoplaneteu-1.0.3.dist-info/RECORD
