Metadata-Version: 2.1
Name: pyExoplaneteu
Version: 1.0.3
Summary: A pure-Python package to download data from the Extrasolar Planets Encyclopaedia
Home-page: https://github.com/j-faria/pyExoplanet.eu
Author: João Faria
Author-email: joao.faria@astro.up.pt
License: MIT
Platform: UNKNOWN
Classifier: Programming Language :: Python :: 3
Classifier: License :: OSI Approved :: MIT License
Classifier: Operating System :: OS Independent
